sap_aicore_llm/RELEASE_INFO
sap_aicore_llm/__init__.py
sap_aicore_llm/ai_core_content_spec.py
sap_aicore_llm/pipelines/workflows.yaml
sap_aicore_llm/pipelines/azure_openai/proxy/Dockerfile
sap_aicore_llm/pipelines/azure_openai/proxy/requirements.txt
sap_aicore_llm/pipelines/azure_openai/proxy/serving_template.yaml
sap_aicore_llm/pipelines/azure_openai/proxy/src/main.py
sap_aicore_llm/pipelines/qa/Dockerfile
sap_aicore_llm/pipelines/qa/requirements.txt
sap_aicore_llm/pipelines/qa/serving_template.yaml
sap_aicore_llm/pipelines/qa/src/index.py
sap_aicore_llm/pipelines/qa/src/query.py
sap_aicore_llm/qa_retrieval/__init__.py
sap_aicore_llm/qa_retrieval/config/__init__.py
sap_aicore_llm/qa_retrieval/manager/__init__.py
sap_aicore_llm/qa_retrieval/manager/indexer.py
sap_aicore_llm/qa_retrieval/manager/retriever.py
sap_aicore_llm/qa_retrieval/model/__init__.py
sap_aicore_llm/qa_retrieval/model/completion.py
sap_aicore_llm/qa_retrieval/model/embedding.py
sap_aicore_llm/qa_retrieval/proxy_client/__init__.py
sap_aicore_llm/qa_retrieval/proxy_client/identity.py
sap_aicore_llm/qa_retrieval/proxy_client/langchain/__init__.py
sap_aicore_llm/qa_retrieval/proxy_client/langchain/openai.py
sap_aicore_llm/qa_retrieval/proxy_client/openai/__init__.py
sap_aicore_llm/qa_retrieval/proxy_client/openai/proxy_api_engine_resource.py
sap_aicore_llm/qa_retrieval/proxy_client/openai/proxy_completion.py
sap_aicore_llm/qa_retrieval/proxy_client/openai/proxy_embedding.py
sap_aicore_llm/qa_retrieval/storage/__init__.py
sap_aicore_llm/qa_retrieval/storage/vector.py
sap_ai_core_llm-1.0.18.dist-info/LICENSE
sap_ai_core_llm-1.0.18.dist-info/METADATA
sap_ai_core_llm-1.0.18.dist-info/WHEEL
sap_ai_core_llm-1.0.18.dist-info/top_level.txt
sap_ai_core_llm-1.0.18.dist-info/RECORD
